measuring_tools/__init__.py
measuring_tools/length.py
measuring_tools/mass.py
measuring_tools/temperature.py
measuring_tools/volume.py
measuring_tools-0.6.0.dist-info/LICENSE
measuring_tools-0.6.0.dist-info/METADATA
measuring_tools-0.6.0.dist-info/WHEEL
measuring_tools-0.6.0.dist-info/top_level.txt
measuring_tools-0.6.0.dist-info/RECORD
